napari_oclrfc/__init__.py
napari_oclrfc/_function.py
napari_oclrfc/_tests/__init__.py
napari_oclrfc/_tests/test_function.py
napari_oclrfc-0.4.6.dist-info/LICENSE
napari_oclrfc-0.4.6.dist-info/METADATA
napari_oclrfc-0.4.6.dist-info/WHEEL
napari_oclrfc-0.4.6.dist-info/entry_points.txt
napari_oclrfc-0.4.6.dist-info/top_level.txt
napari_oclrfc-0.4.6.dist-info/RECORD
