Metadata-Version: 2.1
Name: napari-oclrfc
Version: 0.4.6
Summary: Pixel and label classification using OpenCL-based Random Forest Classifiers
Home-page: https://github.com/haesleinhuepf/napari-oclrfc
Author: Robert Haase
Author-email: robert.haase@tu-dresden.de
License: BSD-3
Project-URL: Bug Tracker, https://github.com/haesleinhuepf/napari-oclrfc/issues
Project-URL: Documentation, https://github.com/haesleinhuepf/napari-oclrfc
Project-URL: Source Code, https://github.com/haesleinhuepf/napari-oclrfc
Project-URL: User Support, https://forum.image.sc/tag/clij
Platform: UNKNOWN
Classifier: Development Status :: 2 - Pre-Alpha
Classifier: Intended Audience :: Science/Research
Classifier: Topic :: Software Development :: Testing
Classifier: Programming Language :: Python
Classifier: Programming Language :: Python :: 3
Classifier: Programming Language :: Python :: 3.7
Classifier: Programming Language :: Python :: 3.8
Classifier: Programming Language :: Python :: 3.9
Classifier: Operating System :: OS Independent
Classifier: License :: OSI Approved :: BSD License
Requires-Python: >=3.7
License-File: LICENSE
Requires-Dist: napari-plugin-engine (>=0.1.4)
Requires-Dist: numpy
Requires-Dist: oclrfc
